lmot/__init__.py
lmot/args.py
lmot/optimize.py
lmot/quantize/__init__.py
lmot/quantize/ldm/__init__.py
lmot/quantize/ldm/controlnet_quant.py
lmot/quantize/ldm/ldm_calib.py
lmot/quantize/ldm/ldm_quant.py
lmot/quantize/ldm/test.py
lmot/quantize/ldm/transformers_quant.py
lmot/quantize/ldm/unet_quant.py
lmot/quantize/ldm/utils.py
lmot/quantize/llm/__init__.py
lmot/quantize/llm/awq.py
lmot/quantize/llm/common.py
lmot/quantize/llm/gptq.py
lmot/quantize/llm/smoothquant.py
lmot/quantize/llm/test.py
lmot/quantize/llm/utils.py
lmot_quant-0.1.1.dist-info/METADATA
lmot_quant-0.1.1.dist-info/WHEEL
lmot_quant-0.1.1.dist-info/top_level.txt
lmot_quant-0.1.1.dist-info/RECORD
